py_dimensional/__init__.py
py_dimensional/hdr.py
py_dimensional/hdr_types.py
py_dimensional-0.0.1.dist-info/METADATA
py_dimensional-0.0.1.dist-info/WHEEL
py_dimensional-0.0.1.dist-info/licenses/LICENSE
py_dimensional-0.0.1.dist-info/RECORD
