Metadata-Version: 2.1
Name: py-dimensional
Version: 0.0.1
Summary: Internet tools for AI agents.
Project-URL: Home page, https://github.com/hdresearch/py-dimensional
Project-URL: Bug Tracker, https://github.com/hdresearch/py-dimensional/issues
Project-URL: Documentation, https://hdr.is/documented/api/v1
Author-email: Tynan Daly <tynan.daly@hdr.is>
License-File: LICENSE
Classifier: Development Status :: 3 - Alpha
Classifier: License :: OSI Approved :: Apache Software License
Classifier: Natural Language :: English
Classifier: Operating System :: OS Independent
Classifier: Programming Language :: Python :: 3
Classifier: Topic :: Communications :: Chat
Classifier: Topic :: Internet
Classifier: Topic :: Internet :: WWW/HTTP :: Indexing/Search
Classifier: Topic :: Scientific/Engineering :: Artificial Intelligence
Classifier: Topic :: Scientific/Engineering :: Human Machine Interfaces
Classifier: Topic :: Text Processing :: Indexing
Classifier: Typing :: Typed
Requires-Python: >=3.8
